CHANGELOG.md
DCO
docs/CHANGELOG.md
pytest_helm_charts/__init__.py
pytest_helm_charts/clusters.py
pytest_helm_charts/errors.py
pytest_helm_charts/fixtures.py
pytest_helm_charts/plugin.py
pytest_helm_charts/utils.py
pytest_helm_charts/flux/__init__.py
pytest_helm_charts/flux/fixtures.py
pytest_helm_charts/flux/git_repository.py
pytest_helm_charts/flux/helm_release.py
pytest_helm_charts/flux/helm_repository.py
pytest_helm_charts/flux/kustomization.py
pytest_helm_charts/flux/utils.py
pytest_helm_charts/giantswarm_app_platform/__init__.py
pytest_helm_charts/giantswarm_app_platform/app.py
pytest_helm_charts/giantswarm_app_platform/app_catalog.py
pytest_helm_charts/giantswarm_app_platform/catalog.py
pytest_helm_charts/giantswarm_app_platform/fixtures.py
pytest_helm_charts/giantswarm_app_platform/apps/__init__.py
pytest_helm_charts/giantswarm_app_platform/apps/http_testing.py
pytest_helm_charts/k8s/__init__.py
pytest_helm_charts/k8s/daemon_set.py
pytest_helm_charts/k8s/deployment.py
pytest_helm_charts/k8s/fixtures.py
pytest_helm_charts/k8s/job.py
pytest_helm_charts/k8s/namespace.py
pytest_helm_charts/k8s/stateful_set.py
pytest_helm_charts-1.3.4.dist-info/METADATA
pytest_helm_charts-1.3.4.dist-info/WHEEL
pytest_helm_charts-1.3.4.dist-info/entry_points.txt
pytest_helm_charts-1.3.4.dist-info/licenses/LICENSE
pytest_helm_charts-1.3.4.dist-info/RECORD
