Metadata-Version: 2.4
Name: pytest-helm-charts
Version: 1.3.4
Summary: A plugin to provide different types and configs of Kubernetes clusters that can be used for testing.
Project-URL: Repository, https://github.com/giantswarm/pytest-helm-charts
Author-email: Łukasz Piątkowski <lukasz@giantswarm.io>
License-Expression: Apache-2.0
License-File: LICENSE
Keywords: chart,helm,kubernetes
Classifier: Development Status :: 4 - Beta
Classifier: Framework :: Pytest
Classifier: Intended Audience :: Developers
Classifier: License :: OSI Approved :: Apache Software License
Classifier: Operating System :: POSIX :: Linux
Classifier: Programming Language :: Python
Classifier: Programming Language :: Python :: 3
Classifier: Programming Language :: Python :: 3.10
Classifier: Programming Language :: Python :: 3.11
Classifier: Programming Language :: Python :: 3.12
Classifier: Programming Language :: Python :: 3.13
Classifier: Programming Language :: Python :: 3.14
Classifier: Programming Language :: Python :: Implementation :: CPython
Classifier: Topic :: Software Development :: Testing
Requires-Python: <4,>=3.10
Requires-Dist: deprecated<2,>=1.2.13
Requires-Dist: pykube-ng<24,>=23.6
Requires-Dist: pytest<9,>=8.0.0
Provides-Extra: docs
Requires-Dist: mkapi<2,>=1.0.14; extra == 'docs'
Requires-Dist: mkdocs<2,>=1.2.3; extra == 'docs'
